PyUtilToolKit/__init__.py
PyUtilToolKit/util_log.py
pypersonalizedutilitykits-1.1.2.dist-info/METADATA
pypersonalizedutilitykits-1.1.2.dist-info/WHEEL
pypersonalizedutilitykits-1.1.2.dist-info/top_level.txt
pypersonalizedutilitykits-1.1.2.dist-info/RECORD
