Metadata-Version: 2.2
Name: pypersonalizedutilitykits
Version: 1.1.2
Summary: Python Personalized Kits
Author: Great people
Author-email: 
License: GPLv3
Keywords: kit
Classifier: Programming Language :: Python :: 3
Classifier: License :: OSI Approved :: GNU General Public License v3 (GPLv3)
Classifier: Operating System :: OS Independent
Requires-Python: >=3.10
Requires-Dist: colorlog==6.8.2
Dynamic: author
Dynamic: classifier
Dynamic: description
Dynamic: keywords
Dynamic: license
Dynamic: requires-dist
Dynamic: requires-python
Dynamic: summary
